[
  { "id": 1, "name": "Abandoned", "type": "neg" },
  { "id": 2, "name": "Accomplished", "type": "pos" },
  { "id": 3, "name": "Aligned", "type": "pos" },
  { "id": 4, "name": "Alienated", "type": "neg" },
  { "id": 5, "name": "Angry", "type": "neg" },
  { "id": 6, "name": "Anxious", "type": "neg" },
  { "id": 7, "name": "Appalled", "type": "neg" },
  { "id": 8, "name": "Appreciated", "type": "pos" },
  { "id": 9, "name": "Assured", "type": "pos" },
  { "id": 10, "name": "Attentive", "type": "pos" },
  { "id": 11, "name": "Autonomous", "type": "pos" },
  { "id": 12, "name": "Balanced", "type": "pos" },
  { "id": 13, "name": "Betrayed", "type": "neg" },
  { "id": 14, "name": "Bored", "type": "neg" },
  { "id": 15, "name": "Burdened", "type": "neg" },
  { "id": 16, "name": "Burned Out", "type": "neg" },
  { "id": 17, "name": "Calm", "type": "pos" },
  { "id": 18, "name": "Capable", "type": "pos" },
  { "id": 19, "name": "Clear", "type": "pos" },
  { "id": 20, "name": "Comfortable", "type": "pos" },
  { "id": 21, "name": "Competent", "type": "pos" },
  { "id": 22, "name": "Composed", "type": "pos" },
  { "id": 23, "name": "Confident", "type": "pos" },
  { "id": 24, "name": "Conflicted", "type": "neg" },
  { "id": 25, "name": "Connected", "type": "pos" },
  { "id": 26, "name": "Considered", "type": "pos" },
  { "id": 27, "name": "Constrained", "type": "neg" },
  { "id": 28, "name": "Content", "type": "pos" },
  { "id": 29, "name": "Controlled", "type": "neg" },
  { "id": 30, "name": "Confused", "type": "neg" },
  { "id": 31, "name": "Certain", "type": "pos" },
  { "id": 32, "name": "Directed", "type": "pos" },
  { "id": 33, "name": "Directionless", "type": "neg" },
  { "id": 34, "name": "Disempowered", "type": "neg" },
  { "id": 35, "name": "Disconnected", "type": "neg" },
  { "id": 36, "name": "Discriminated", "type": "neg" },
  { "id": 37, "name": "Disoriented", "type": "neg" },
  { "id": 38, "name": "Distracted", "type": "neg" },
  { "id": 39, "name": "Distrustful", "type": "neg" },
  { "id": 40, "name": "Drained", "type": "neg" },
  { "id": 41, "name": "Efficient", "type": "pos" },
  { "id": 42, "name": "Embarrassed", "type": "neg" },
  { "id": 43, "name": "Empty", "type": "neg" },
  { "id": 44, "name": "Empowered", "type": "pos" },
  { "id": 45, "name": "Energized", "type": "pos" },
  { "id": 46, "name": "Engaged", "type": "pos" },
  { "id": 47, "name": "Equipped", "type": "pos" },
  { "id": 48, "name": "Excluded", "type": "neg" },
  { "id": 49, "name": "Exhausted", "type": "neg" },
  { "id": 50, "name": "Fair", "type": "pos" },
  { "id": 51, "name": "Fearful", "type": "neg" },
  { "id": 52, "name": "Flexible", "type": "pos" },
  { "id": 53, "name": "Focused", "type": "pos" },
  { "id": 54, "name": "Frazzled", "type": "neg" },
  { "id": 55, "name": "Frustrated", "type": "neg" },
  { "id": 56, "name": "Fulfilled", "type": "pos" },
  { "id": 57, "name": "Guided", "type": "pos" },
  { "id": 58, "name": "Harmonious", "type": "pos" },
  { "id": 59, "name": "Harmonized", "type": "pos" },
  { "id": 60, "name": "Healthy", "type": "pos" },
  { "id": 61, "name": "Heard", "type": "pos" },
  { "id": 62, "name": "Helpless", "type": "neg" },
  { "id": 63, "name": "Hindered", "type": "neg" },
  { "id": 64, "name": "Humiliated", "type": "neg" },
  { "id": 65, "name": "Hurt", "type": "neg" },
  { "id": 66, "name": "Ill-equipped", "type": "neg" },
  { "id": 67, "name": "Imbalanced", "type": "neg" },
  { "id": 68, "name": "Impeded", "type": "neg" },
  { "id": 69, "name": "Inadequate", "type": "neg" },
  { "id": 70, "name": "Included", "type": "pos" },
  { "id": 71, "name": "Independent", "type": "pos" },
  { "id": 72, "name": "Ineffective", "type": "neg" },
  { "id": 73, "name": "Influential", "type": "pos" },
  { "id": 74, "name": "Informed", "type": "pos" },
  { "id": 75, "name": "In Control", "type": "pos" },
  { "id": 76, "name": "Insecure", "type": "neg" },
  { "id": 77, "name": "Interested", "type": "pos" },
  { "id": 78, "name": "Intimidated", "type": "neg" },
  { "id": 79, "name": "Invaded", "type": "neg" },
  { "id": 80, "name": "Invisible", "type": "neg" },
  { "id": 81, "name": "Involved", "type": "pos" },
  { "id": 82, "name": "Ignored", "type": "neg" },
  { "id": 83, "name": "Isolated", "type": "neg" },
  { "id": 84, "name": "Lonely", "type": "neg" },
  { "id": 85, "name": "Lost", "type": "neg" },
  { "id": 86, "name": "Manageable", "type": "pos" },
  { "id": 87, "name": "Marginalised", "type": "neg" },
  { "id": 88, "name": "Misled", "type": "neg" },
  { "id": 89, "name": "Misunderstood", "type": "neg" },
  { "id": 90, "name": "Motivated", "type": "pos" },
  { "id": 91, "name": "Overburdened", "type": "neg" },
  { "id": 92, "name": "Overloaded", "type": "neg" },
  { "id": 93, "name": "Overwhelmed", "type": "neg" },
  { "id": 94, "name": "Overworked", "type": "neg" },
  { "id": 95, "name": "Powerless", "type": "neg" },
  { "id": 96, "name": "Predictable", "type": "pos" },
  { "id": 97, "name": "Prepared", "type": "pos" },
  { "id": 98, "name": "Pressured", "type": "neg" },
  { "id": 99, "name": "Protected", "type": "pos" },
  { "id": 100, "name": "Purposeful", "type": "pos" },
  { "id": 101, "name": "Reassured", "type": "pos" },
  { "id": 102, "name": "Refreshed", "type": "pos" },
  { "id": 103, "name": "Relaxed", "type": "pos" },
  { "id": 104, "name": "Respected", "type": "pos" },
  { "id": 105, "name": "Responsible", "type": "pos" },
  { "id": 106, "name": "Restricted", "type": "neg" },
  { "id": 107, "name": "Resentful", "type": "neg" },
  { "id": 108, "name": "Safe", "type": "pos" },
  { "id": 109, "name": "Satisfied", "type": "pos" },
  { "id": 110, "name": "Scared", "type": "neg" },
  { "id": 111, "name": "Secure", "type": "pos" },
  { "id": 112, "name": "Stable", "type": "pos" },
  { "id": 113, "name": "Stagnant", "type": "neg" },
  { "id": 114, "name": "Steady", "type": "pos" },
  { "id": 115, "name": "Stimulated", "type": "pos" },
  { "id": 116, "name": "Stressed", "type": "neg" },
  { "id": 117, "name": "Supported", "type": "pos" },
  { "id": 118, "name": "Targeted", "type": "neg" },
  { "id": 119, "name": "Threatened", "type": "neg" },
  { "id": 120, "name": "Trapped", "type": "neg" },
  { "id": 121, "name": "Traumatised", "type": "neg" },
  { "id": 122, "name": "Trusted", "type": "pos" },
  { "id": 123, "name": "Uneasy", "type": "neg" },
  { "id": 124, "name": "Unappreciated", "type": "neg" },
  { "id": 125, "name": "Unbalanced", "type": "neg" },
  { "id": 126, "name": "Uncertain", "type": "neg" },
  { "id": 127, "name": "Uncomfortable", "type": "neg" },
  { "id": 128, "name": "Undermined", "type": "neg" },
  { "id": 129, "name": "Underutilized", "type": "neg" },
  { "id": 130, "name": "Unfocused", "type": "neg" },
  { "id": 131, "name": "Unfulfilled", "type": "neg" },
  { "id": 132, "name": "Unheard", "type": "neg" },
  { "id": 133, "name": "Uninformed", "type": "neg" },
  { "id": 134, "name": "Uninspired", "type": "neg" },
  { "id": 135, "name": "Unmotivated", "type": "neg" },
  { "id": 136, "name": "Unprepared", "type": "neg" },
  { "id": 137, "name": "Unsafe", "type": "neg" },
  { "id": 138, "name": "Unsettled", "type": "neg" },
  { "id": 139, "name": "Unsupported", "type": "neg" },
  { "id": 140, "name": "Unsure", "type": "neg" },
  { "id": 141, "name": "Unstable", "type": "neg" },
  { "id": 142, "name": "Unstressed", "type": "pos" },
  { "id": 143, "name": "Untroubled", "type": "pos" },
  { "id": 144, "name": "Unvalued", "type": "neg" },
  { "id": 145, "name": "Valued", "type": "pos" },
  { "id": 146, "name": "Victimized", "type": "neg" },
  { "id": 147, "name": "Violated", "type": "neg" },
  { "id": 148, "name": "Vulnerable", "type": "neg" },
  { "id": 149, "name": "Wasted", "type": "neg" },
  { "id": 150, "name": "Worried", "type": "neg" }
]
